pytest_wa_e2e_plugin/__init__.py
pytest_wa_e2e_plugin/plugin.py
pytest_wa_e2e_plugin/utils.py
pytest_wa_e2e_plugin-0.1.3.dist-info/LICENSE
pytest_wa_e2e_plugin-0.1.3.dist-info/METADATA
pytest_wa_e2e_plugin-0.1.3.dist-info/WHEEL
pytest_wa_e2e_plugin-0.1.3.dist-info/entry_points.txt
pytest_wa_e2e_plugin-0.1.3.dist-info/top_level.txt
pytest_wa_e2e_plugin-0.1.3.dist-info/RECORD
